[
  {
    "norm": "wertyservyt",
    "display": "Werty-Servyt",
    "initial": 212290,
    "current": 309940,
    "diff": 97650,
    "avatar": "avatars/wertyservyt.jpg",
    "profile": "https://remanga.org/user/364625/about",
    "guild": "Eternal Watchers",
    "is_afk": true,
    "last_active_human": "22 дн. назад"
  },
  {
    "norm": "бeлoхвoctый",
    "display": "Белохвостый",
    "initial": 51100,
    "current": 145000,
    "diff": 93900,
    "avatar": "avatars/бeлoхвoctый.jpg",
    "profile": "https://remanga.org/user/2874672/about",
    "guild": "Eternal Watchers",
    "is_afk": false,
    "last_active_human": "вчера"
  },
  {
    "norm": "pepegaronni",
    "display": "Pepegaronni",
    "initial": 28630,
    "current": 102650,
    "diff": 74020,
    "avatar": "avatars/pepegaronni.jpg",
    "profile": "https://remanga.org/user/27168/about",
    "guild": "Eternal Watchers",
    "is_afk": false,
    "last_active_human": "4 дн. назад"
  },
  {
    "norm": "akiragame",
    "display": "AkiraGame",
    "initial": 61970,
    "current": 135000,
    "diff": 73030,
    "avatar": "avatars/akiragame.jpg",
    "profile": "https://remanga.org/user/1714962/about",
    "guild": "Eternal Watchers",
    "is_afk": false,
    "last_active_human": "сегодня"
  },
  {
    "norm": "belashik",
    "display": "Belashik",
    "initial": 149100,
    "current": 208000,
    "diff": 58900,
    "avatar": "avatars/belashik.jpg",
    "profile": "https://remanga.org/user/175047/about",
    "guild": "Eternal Watchers",
    "is_afk": false,
    "last_active_human": "вчера"
  },
  {
    "norm": "tenofmoses",
    "display": "tenofmoses",
    "initial": 0,
    "current": 56600,
    "diff": 56600,
    "avatar": "avatars/tenofmoses.jpg",
    "profile": "https://remanga.org/user/3176212/about",
    "guild": "Eternal Watchers",
    "is_afk": false,
    "last_active_human": "сегодня"
  },
  {
    "norm": "akiram",
    "display": "Aki_Ram",
    "initial": 28600,
    "current": 85120,
    "diff": 56520,
    "avatar": "avatars/akiram.jpg",
    "profile": "https://remanga.org/user/3307870/about",
    "guild": "Eternal Watchers",
    "is_afk": false,
    "last_active_human": "5 дн. назад"
  },
  {
    "norm": "caйtaмa",
    "display": "Сайтама",
    "initial": 128060,
    "current": 181450,
    "diff": 53390,
    "avatar": "avatars/placeholder.jpg",
    "profile": "https://remanga.org/user/12762/about",
    "guild": "Eternal Watchers",
    "is_afk": false,
    "last_active_human": "вчера"
  },
  {
    "norm": "festashka",
    "display": "_festashka_",
    "initial": 77750,
    "current": 126600,
    "diff": 48850,
    "avatar": "avatars/festashka.jpg",
    "profile": "https://remanga.org/user/199911/about",
    "guild": "Eternal Watchers",
    "is_afk": false,
    "last_active_human": "вчера"
  },
  {
    "norm": "кaйдeн",
    "display": "Кайден",
    "initial": 64610,
    "current": 109500,
    "diff": 44890,
    "avatar": "avatars/кaйдeн.jpg",
    "profile": "https://remanga.org/user/439629/about",
    "guild": "Eternal Watchers",
    "is_afk": false,
    "last_active_human": "сегодня"
  }
]